calc_sdk/__init__.py
calc_sdk/calculator.py
calc_test_sdk-1.0.0.dist-info/licenses/LICENSE
calc_test_sdk-1.0.0.dist-info/METADATA
calc_test_sdk-1.0.0.dist-info/WHEEL
calc_test_sdk-1.0.0.dist-info/top_level.txt
calc_test_sdk-1.0.0.dist-info/RECORD
